footysim/__init__.py
footysim/cli.py
footysim/core/config.py
footysim/core/exceptions.py
footysim/core/logging.py
footysim/db/base.py
footysim/db/session.py
footysim/models/__init__.py
footysim/models/club.py
footysim/models/country.py
footysim/models/fixture.py
footysim/models/goal.py
footysim/models/league.py
footysim/models/match.py
footysim/models/player.py
footysim/models/season.py
footysim/models/stadium.py
footysim/models/transfer.py
footysim/repositories/base.py
footysim/repositories/clubs.py
footysim/repositories/fixtures.py
footysim/repositories/matches.py
footysim/repositories/players.py
footysim/seeds/seed_data.py
footysim/services/match_engine.py
footysim/services/schedule_service.py
footysim/services/table_service.py
footysim_core-0.1.16.dist-info/METADATA
footysim_core-0.1.16.dist-info/WHEEL
footysim_core-0.1.16.dist-info/entry_points.txt
footysim_core-0.1.16.dist-info/top_level.txt
footysim_core-0.1.16.dist-info/RECORD
