Metadata-Version: 2.4
Name: footysim-core
Version: 0.1.16
Summary: FootySim Core — async SQLAlchemy models, services & CLI for football simulations
Author-email: Louis BERTRAND <louisbert91@gmail.com>
License: MIT
Requires-Python: >=3.11
Requires-Dist: SQLAlchemy>=2.0
Requires-Dist: alembic>=1.13
Requires-Dist: python-dotenv>=1.0
Requires-Dist: typer>=0.12.0
Requires-Dist: pydantic>=2.0
Requires-Dist: aiosqlite>=0.20.0
Requires-Dist: greenlet>=3.0
Provides-Extra: mysql
Requires-Dist: aiomysql>=0.2.0; extra == "mysql"
Provides-Extra: dev
Requires-Dist: pytest; extra == "dev"
Requires-Dist: ruff; extra == "dev"
Requires-Dist: build; extra == "dev"
